Workbook

Sheet Legend
A1: Risk Register: How to Use This Workbook
A2: Formula-driven register built from ITGC testing, a vulnerability assessment and an enterprise risk list
A4: Sheets
A5: Register | B5: One row per risk. Edit the blue cells. Scores, ratings, flags and rank are formulas.
A6: Heat Map | B6: 5x5 likelihood and impact grids (inherent and residual) with live risk counts per cell.
A7: Summary | B7: Counts by rating, status, source and category, plus the top 5 risks and a chart.
A8: Scale | B8: Rating thresholds, report as-of date, and the 1-5 likelihood and impact definitions.
A10: Cell colour key
A11: Blue text | B11: Input. Safe to change.
A12: Black text | B12: Formula. Do not overwrite.
A14: To add a risk | B14: Copy the last filled row on Register down one row (formulas included) and edit the blue cells. Formulas on Heat Map and Summary read rows 5 to 54 of Register.
A15: To change the rating bands | B15: Edit the minimum scores on Scale (B5:B8). Ratings and heat map colours update.
A16: To change the as-of date | B16: Edit Scale!B11. Days to Target and the OVERDUE flag update. Use =TODAY() there for a live view.
A18: Assumptions
A19: Scoring | B19: Score = likelihood x impact, each 1 to 5, giving 1 to 25. Same bands as the risk-register-tracker repo.
A20: Inherent vs residual | B20: Inherent = before the planned mitigation. Residual = after it is fully in place (a target, not a measurement).
A21: Sources | B21: R-01 to R-04 come from the itgc-controls-testing repo. R-05 to R-08 come from the vulnerability-assessment-report repo. R-09 to R-15 are the enterprise risks from the risk-register-tracker repo.
A22: Rescaling | B22: The vulnerability assessment scored on a 1 to 3 scale. Those risks are rescored here on 1 to 5; the original scores are recorded in each description. The new scores are my judgment, not measured data.
A23: Data | B23: All data is synthetic and for portfolio demonstration. Dates and owners are illustrative.

Sheet Register
A1: Risk Register
A2: Blue cells are inputs; black cells are formulas. Rows 5 to 54 feed the other sheets.
A4: Risk ID | B4: Risk Title | C4: Category | D4: Source | E4: Description | F4: Likelihood (1-5) | G4: Impact (1-5) | H4: Inherent Score | I4: Inherent Rating | J4: Risk Owner | K4: Treatment | L4: Mitigation / Response | M4: Residual Likelihood | N4: Residual Impact | O4: Residual Score | P4: Residual Rating | Q4: Risk Reduction | R4: Status | S4: Target Date | T4: Days to Target | U4: Overdue? | V4: Rank Key (helper)
A5: R-01 | B5: Terminated users retain active ERP access | C5: Access Control | D5: ITGC Testing | E5: Control 1 test: U1003 (terminated 2026-05-15) and U1010 (terminated 2026-06-02) were still Active in the finance ERP at the 2026-06-15 audit date. | F5: 4 | G5: 4 | H5: =F5*G5 -> 16 | I5: =IF(H5>=Scale!$B$8,"Critical",IF(H5>=Scale!$B$7,"High",IF(H5>=Scale!$B$6,"Medium","Low"))) -> Critical | J5: IT Security | K5: Mitigate | L5: Disable both accounts now; trigger deprovisioning from HR termination events; reconcile HR terminations to active accounts monthly. | M5: 1 | N5: 4 | O5: =M5*N5 -> 4 | P5: =IF(O5>=Scale!$B$8,"Critical",IF(O5>=Scale!$B$7,"High",IF(O5>=Scale!$B$6,"Medium","Low"))) -> Low | Q5: =IF(H5=0,0,(H5-O5)/H5) -> 0.75 | R5: In Progress | S5: 46310 | T5: =IF(R5="Closed","",S5-Scale!$B$11) -> -15 | U5: =IF(AND(R5<>"Closed",S5<Scale!$B$11),"OVERDUE","") -> OVERDUE | V5: =H5+(1000-ROW())/100000 -> 16.00995
A6: R-02 | B6: Periodic access reviews overdue | C6: Access Control | D6: ITGC Testing | E6: Control 2 test: U1010 (last review 2025-11-01) and U1016 (2025-09-01) are past the six-month review cycle. | F6: 3 | G6: 3 | H6: =F6*G6 -> 9 | I6: =IF(H6>=Scale!$B$8,"Critical",IF(H6>=Scale!$B$7,"High",IF(H6>=Scale!$B$6,"Medium","Low"))) -> Medium | J6: Finance Controller | K6: Mitigate | L6: Complete the overdue reviews; calendar semi-annual recertification with manager sign-off tracked to completion. | M6: 1 | N6: 3 | O6: =M6*N6 -> 3 | P6: =IF(O6>=Scale!$B$8,"Critical",IF(O6>=Scale!$B$7,"High",IF(O6>=Scale!$B$6,"Medium","Low"))) -> Low | Q6: =IF(H6=0,0,(H6-O6)/H6) -> 0.66666667 | R6: In Progress | S6: 46356 | T6: =IF(R6="Closed","",S6-Scale!$B$11) -> 31 | U6: =IF(AND(R6<>"Closed",S6<Scale!$B$11),"OVERDUE","") | V6: =H6+(1000-ROW())/100000 -> 9.00994
A7: R-03 | B7: Production changes without independent approval | C7: Change Management | D7: ITGC Testing | E7: Control 3 test: CH-2203 and CH-2207 had no approver; CH-2206 was approved (2026-05-18) after it was implemented (2026-05-14); CH-2208 was self-approved. | F7: 4 | G7: 4 | H7: =F7*G7 -> 16 | I7: =IF(H7>=Scale!$B$8,"Critical",IF(H7>=Scale!$B$7,"High",IF(H7>=Scale!$B$6,"Medium","Low"))) -> Critical | J7: IT Infrastructure | K7: Mitigate | L7: Block deployment in the ticketing system until an independent approval is logged; prevent requester from approving own change; review the four changes after the fact. | M7: 2 | N7: 4 | O7: =M7*N7 -> 8 | P7: =IF(O7>=Scale!$B$8,"Critical",IF(O7>=Scale!$B$7,"High",IF(O7>=Scale!$B$6,"Medium","Low"))) -> Medium | Q7: =IF(H7=0,0,(H7-O7)/H7) -> 0.5 | R7: Open | S7: 46371 | T7: =IF(R7="Closed","",S7-Scale!$B$11) -> 46 | U7: =IF(AND(R7<>"Closed",S7<Scale!$B$11),"OVERDUE","") | V7: =H7+(1000-ROW())/100000 -> 16.00993
A8: R-04 | B8: AP and Purchasing roles held by one user | C8: Segregation of Duties | D8: ITGC Testing | E8: Control 4 test: U1016 holds AP Clerk and Purchasing Agent, so one person can create a purchase order and process its payment. | F8: 3 | G8: 4 | H8: =F8*G8 -> 12 | I8: =IF(H8>=Scale!$B$8,"Critical",IF(H8>=Scale!$B$7,"High",IF(H8>=Scale!$B$6,"Medium","Low"))) -> High | J8: Finance Controller | K8: Mitigate | L8: Remove the Purchasing Agent role, or add supervisor review of all payments this user processes until it is removed. | M8: 1 | N8: 4 | O8: =M8*N8 -> 4 | P8: =IF(O8>=Scale!$B$8,"Critical",IF(O8>=Scale!$B$7,"High",IF(O8>=Scale!$B$6,"Medium","Low"))) -> Low | Q8: =IF(H8=0,0,(H8-O8)/H8) -> 0.66666667 | R8: Open | S8: 46341 | T8: =IF(R8="Closed","",S8-Scale!$B$11) -> 16 | U8: =IF(AND(R8<>"Closed",S8<Scale!$B$11),"OVERDUE","") | V8: =H8+(1000-ROW())/100000 -> 12.00992
A9: R-05 | B9: Customer database reachable from the public internet | C9: Network Security | D9: Vulnerability Assessment | E9: The customer database server has accepted connections from any public address since launch. Assessment scored data exfiltration 3x3 on a 1-3 scale; rescored 4x5 here. | F9: 4 | G9: 5 | H9: =F9*G9 -> 20 | I9: =IF(H9>=Scale!$B$8,"Critical",IF(H9>=Scale!$B$7,"High",IF(H9>=Scale!$B$6,"Medium","Low"))) -> Critical | J9: IT Infrastructure | K9: Mitigate | L9: Restrict inbound access to an allow-list of office and VPN egress addresses; require MFA for administrative access. | M9: 1 | N9: 5 | O9: =M9*N9 -> 5 | P9: =IF(O9>=Scale!$B$8,"Critical",IF(O9>=Scale!$B$7,"High",IF(O9>=Scale!$B$6,"Medium","Low"))) -> Medium | Q9: =IF(H9=0,0,(H9-O9)/H9) -> 0.75 | R9: Open | S9: 46387 | T9: =IF(R9="Closed","",S9-Scale!$B$11) -> 62 | U9: =IF(AND(R9<>"Closed",S9<Scale!$B$11),"OVERDUE","") | V9: =H9+(1000-ROW())/100000 -> 20.00991
A10: R-06 | B10: Automated scanners find the exposed database | C10: Network Security | D10: Vulnerability Assessment | E10: Public database ports are scanned continuously and can become a foothold for further attacks. Assessment scored 3x2; rescored 5x3 here. | F10: 5 | G10: 3 | H10: =F10*G10 -> 15 | I10: =IF(H10>=Scale!$B$8,"Critical",IF(H10>=Scale!$B$7,"High",IF(H10>=Scale!$B$6,"Medium","Low"))) -> Critical | J10: IT Infrastructure | K10: Mitigate | L10: Same allow-list as R-05; alert on connection attempts from outside the allow-list. | M10: 1 | N10: 3 | O10: =M10*N10 -> 3 | P10: =IF(O10>=Scale!$B$8,"Critical",IF(O10>=Scale!$B$7,"High",IF(O10>=Scale!$B$6,"Medium","Low"))) -> Low | Q10: =IF(H10=0,0,(H10-O10)/H10) -> 0.8 | R10: Open | S10: 46387 | T10: =IF(R10="Closed","",S10-Scale!$B$11) -> 62 | U10: =IF(AND(R10<>"Closed",S10<Scale!$B$11),"OVERDUE","") | V10: =H10+(1000-ROW())/100000 -> 15.0099
A11: R-07 | B11: Employee alters or deletes customer records | C11: Data Protection | D11: Vulnerability Assessment | E11: A malicious or careless employee changes or deletes records, disrupting sales operations. Assessment scored 2x2; rescored 2x3 here. | F11: 2 | G11: 3 | H11: =F11*G11 -> 6 | I11: =IF(H11>=Scale!$B$8,"Critical",IF(H11>=Scale!$B$7,"High",IF(H11>=Scale!$B$6,"Medium","Low"))) -> Medium | J11: IT Security | K11: Mitigate | L11: Role-based access with read-only query access for sales staff; audit logging on write operations. | M11: 1 | N11: 3 | O11: =M11*N11 -> 3 | P11: =IF(O11>=Scale!$B$8,"Critical",IF(O11>=Scale!$B$7,"High",IF(O11>=Scale!$B$6,"Medium","Low"))) -> Low | Q11: =IF(H11=0,0,(H11-O11)/H11) -> 0.5 | R11: Open | S11: 46418 | T11: =IF(R11="Closed","",S11-Scale!$B$11) -> 93 | U11: =IF(AND(R11<>"Closed",S11<Scale!$B$11),"OVERDUE","") | V11: =H11+(1000-ROW())/100000 -> 6.00989
A12: R-08 | B12: Database connections use deprecated SSL | C12: Data Protection | D12: Vulnerability Assessment | E12: The assessment recommended moving from SSL to TLS 1.2 or higher on all permitted connections because SSL has known weaknesses. | F12: 3 | G12: 3 | H12: =F12*G12 -> 9 | I12: =IF(H12>=Scale!$B$8,"Critical",IF(H12>=Scale!$B$7,"High",IF(H12>=Scale!$B$6,"Medium","Low"))) -> Medium | J12: IT Infrastructure | K12: Mitigate | L12: Disable SSL, enforce TLS 1.2 or higher, and confirm with a configuration scan. | M12: 1 | N12: 3 | O12: =M12*N12 -> 3 | P12: =IF(O12>=Scale!$B$8,"Critical",IF(O12>=Scale!$B$7,"High",IF(O12>=Scale!$B$6,"Medium","Low"))) -> Low | Q12: =IF(H12=0,0,(H12-O12)/H12) -> 0.66666667 | R12: Open | S12: 46371 | T12: =IF(R12="Closed","",S12-Scale!$B$11) -> 46 | U12: =IF(AND(R12<>"Closed",S12<Scale!$B$11),"OVERDUE","") | V12: =H12+(1000-ROW())/100000 -> 9.00988
A13: R-09 | B13: Unpatched ERP server vulnerability | C13: Vulnerability Management | D13: Enterprise Register | E13: Critical CVE identified on the production ERP application server; no patch applied yet. | F13: 4 | G13: 5 | H13: =F13*G13 -> 20 | I13: =IF(H13>=Scale!$B$8,"Critical",IF(H13>=Scale!$B$7,"High",IF(H13>=Scale!$B$6,"Medium","Low"))) -> Critical | J13: IT Infrastructure | K13: Mitigate | L13: Apply the vendor patch in the next maintenance window; add a compensating WAF rule in the interim. | M13: 2 | N13: 5 | O13: =M13*N13 -> 10 | P13: =IF(O13>=Scale!$B$8,"Critical",IF(O13>=Scale!$B$7,"High",IF(O13>=Scale!$B$6,"Medium","Low"))) -> High | Q13: =IF(H13=0,0,(H13-O13)/H13) -> 0.5 | R13: In Progress | S13: 46346 | T13: =IF(R13="Closed","",S13-Scale!$B$11) -> 21 | U13: =IF(AND(R13<>"Closed",S13<Scale!$B$11),"OVERDUE","") | V13: =H13+(1000-ROW())/100000 -> 20.00987
A14: R-10 | B14: No MFA on remote VPN access | C14: Access Control | D14: Enterprise Register | E14: Remote access to the internal network does not require multi-factor authentication. | F14: 3 | G14: 5 | H14: =F14*G14 -> 15 | I14: =IF(H14>=Scale!$B$8,"Critical",IF(H14>=Scale!$B$7,"High",IF(H14>=Scale!$B$6,"Medium","Low"))) -> Critical | J14: IT Security | K14: Mitigate | L14: Roll out MFA enforcement for all VPN users. | M14: 1 | N14: 5 | O14: =M14*N14 -> 5 | P14: =IF(O14>=Scale!$B$8,"Critical",IF(O14>=Scale!$B$7,"High",IF(O14>=Scale!$B$6,"Medium","Low"))) -> Medium | Q14: =IF(H14=0,0,(H14-O14)/H14) -> 0.66666667 | R14: Open | S14: 46357 | T14: =IF(R14="Closed","",S14-Scale!$B$11) -> 32 | U14: =IF(AND(R14<>"Closed",S14<Scale!$B$11),"OVERDUE","") | V14: =H14+(1000-ROW())/100000 -> 15.00986
A15: R-11 | B15: No tested ransomware response runbook | C15: Incident Response | D15: Enterprise Register | E15: The organization has no documented, tested runbook for a ransomware scenario. | F15: 3 | G15: 5 | H15: =F15*G15 -> 15 | I15: =IF(H15>=Scale!$B$8,"Critical",IF(H15>=Scale!$B$7,"High",IF(H15>=Scale!$B$6,"Medium","Low"))) -> Critical | J15: IT Security | K15: Mitigate | L15: Draft the runbook and run a tabletop exercise to test it. | M15: 2 | N15: 5 | O15: =M15*N15 -> 10 | P15: =IF(O15>=Scale!$B$8,"Critical",IF(O15>=Scale!$B$7,"High",IF(O15>=Scale!$B$6,"Medium","Low"))) -> High | Q15: =IF(H15=0,0,(H15-O15)/H15) -> 0.33333333 | R15: Open | S15: 46402 | T15: =IF(R15="Closed","",S15-Scale!$B$11) -> 77 | U15: =IF(AND(R15<>"Closed",S15<Scale!$B$11),"OVERDUE","") | V15: =H15+(1000-ROW())/100000 -> 15.00985
A16: R-12 | B16: Shared admin credentials on legacy file server | C16: Access Control | D16: Enterprise Register | E16: A legacy file server uses one shared administrator account instead of individual accounts. | F16: 4 | G16: 3 | H16: =F16*G16 -> 12 | I16: =IF(H16>=Scale!$B$8,"Critical",IF(H16>=Scale!$B$7,"High",IF(H16>=Scale!$B$6,"Medium","Low"))) -> High | J16: IT Infrastructure | K16: Mitigate | L16: Migrate to individual admin accounts with logging enabled. | M16: 1 | N16: 3 | O16: =M16*N16 -> 3 | P16: =IF(O16>=Scale!$B$8,"Critical",IF(O16>=Scale!$B$7,"High",IF(O16>=Scale!$B$6,"Medium","Low"))) -> Low | Q16: =IF(H16=0,0,(H16-O16)/H16) -> 0.75 | R16: Open | S16: 46356 | T16: =IF(R16="Closed","",S16-Scale!$B$11) -> 31 | U16: =IF(AND(R16<>"Closed",S16<Scale!$B$11),"OVERDUE","") | V16: =H16+(1000-ROW())/100000 -> 12.00984
... A19: R-15 | B19: Critical vendor risk assessments out of date | C19: Third-Party Risk | D19: Enterprise Register | E19: Several critical vendors have not been reassessed in over 18 months. | F19: 3 | G19: 3 | H19: =F19*G19 -> 9 | I19: =IF(H19>=Scale!$B$8,"Critical",IF(H19>=Scale!$B$7,"High",IF(H19>=Scale!$B$6,"Medium","Low"))) -> Medium | J19: Procurement | K19: Mitigate | L19: Reassess all critical vendors now and move to a 12-month cycle. | M19: 2 | N19: 3 | O19: =M19*N19 -> 6 | P19: =IF(O19>=Scale!$B$8,"Critical",IF(O19>=Scale!$B$7,"High",IF(O19>=Scale!$B$6,"Medium","Low"))) -> Medium | Q19: =IF(H19=0,0,(H19-O19)/H19) -> 0.33333333 | R19: Open | S19: 46419 | T19: =IF(R19="Closed","",S19-Scale!$B$11) -> 94 | U19: =IF(AND(R19<>"Closed",S19<Scale!$B$11),"OVERDUE","") | V19: =H19+(1000-ROW())/100000 -> 9.00981

Sheet Heat Map
A1: Risk Heat Maps
A2: Each cell counts the risks at that likelihood and impact. Colour = rating band for that cell.
A4: Inherent risk (before mitigation)
C5: Likelihood
C6: 1 | D6: 2 | E6: 3 | F6: 4 | G6: 5
A7: Impact | B7: 5 | C7: =COUNTIFS(Register!$F$5:$F$54,C$6,Register!$G$5:$G$54,$B7) -> 0 | D7: =COUNTIFS(Register!$F$5:$F$54,D$6,Register!$G$5:$G$54,$B7) -> 1 | E7: =COUNTIFS(Register!$F$5:$F$54,E$6,Register!$G$5:$G$54,$B7) -> 2 | F7: =COUNTIFS(Register!$F$5:$F$54,F$6,Register!$G$5:$G$54,$B7) -> 2 | G7: =COUNTIFS(Register!$F$5:$F$54,G$6,Register!$G$5:$G$54,$B7) -> 0
B8: 4 | C8: =COUNTIFS(Register!$F$5:$F$54,C$6,Register!$G$5:$G$54,$B8) -> 0 | D8: =COUNTIFS(Register!$F$5:$F$54,D$6,Register!$G$5:$G$54,$B8) -> 0 | E8: =COUNTIFS(Register!$F$5:$F$54,E$6,Register!$G$5:$G$54,$B8) -> 2 | F8: =COUNTIFS(Register!$F$5:$F$54,F$6,Register!$G$5:$G$54,$B8) -> 2 | G8: =COUNTIFS(Register!$F$5:$F$54,G$6,Register!$G$5:$G$54,$B8) -> 0
B9: 3 | C9: =COUNTIFS(Register!$F$5:$F$54,C$6,Register!$G$5:$G$54,$B9) -> 0 | D9: =COUNTIFS(Register!$F$5:$F$54,D$6,Register!$G$5:$G$54,$B9) -> 1 | E9: =COUNTIFS(Register!$F$5:$F$54,E$6,Register!$G$5:$G$54,$B9) -> 3 | F9: =COUNTIFS(Register!$F$5:$F$54,F$6,Register!$G$5:$G$54,$B9) -> 1 | G9: =COUNTIFS(Register!$F$5:$F$54,G$6,Register!$G$5:$G$54,$B9) -> 1
B10: 2 | C10: =COUNTIFS(Register!$F$5:$F$54,C$6,Register!$G$5:$G$54,$B10) -> 0 | D10: =COUNTIFS(Register!$F$5:$F$54,D$6,Register!$G$5:$G$54,$B10) -> 0 | E10: =COUNTIFS(Register!$F$5:$F$54,E$6,Register!$G$5:$G$54,$B10) -> 0 | F10: =COUNTIFS(Register!$F$5:$F$54,F$6,Register!$G$5:$G$54,$B10) -> 0 | G10: =COUNTIFS(Register!$F$5:$F$54,G$6,Register!$G$5:$G$54,$B10) -> 0
B11: 1 | C11: =COUNTIFS(Register!$F$5:$F$54,C$6,Register!$G$5:$G$54,$B11) -> 0 | D11: =COUNTIFS(Register!$F$5:$F$54,D$6,Register!$G$5:$G$54,$B11) -> 0 | E11: =COUNTIFS(Register!$F$5:$F$54,E$6,Register!$G$5:$G$54,$B11) -> 0 | F11: =COUNTIFS(Register!$F$5:$F$54,F$6,Register!$G$5:$G$54,$B11) -> 0 | G11: =COUNTIFS(Register!$F$5:$F$54,G$6,Register!$G$5:$G$54,$B11) -> 0
B12: Total | C12: =SUM(C7:G11) -> 15
A16: Residual risk (after planned mitigation)
C17: Likelihood
C18: 1 | D18: 2 | E18: 3 | F18: 4 | G18: 5
A19: Impact | B19: 5 | C19: =COUNTIFS(Register!$M$5:$M$54,C$18,Register!$N$5:$N$54,$B19) -> 3 | D19: =COUNTIFS(Register!$M$5:$M$54,D$18,Register!$N$5:$N$54,$B19) -> 2 | E19: =COUNTIFS(Register!$M$5:$M$54,E$18,Register!$N$5:$N$54,$B19) -> 0 | F19: =COUNTIFS(Register!$M$5:$M$54,F$18,Register!$N$5:$N$54,$B19) -> 0 | G19: =COUNTIFS(Register!$M$5:$M$54,G$18,Register!$N$5:$N$54,$B19) -> 0
B20: 4 | C20: =COUNTIFS(Register!$M$5:$M$54,C$18,Register!$N$5:$N$54,$B20) -> 3 | D20: =COUNTIFS(Register!$M$5:$M$54,D$18,Register!$N$5:$N$54,$B20) -> 1 | E20: =COUNTIFS(Register!$M$5:$M$54,E$18,Register!$N$5:$N$54,$B20) -> 0 | F20: =COUNTIFS(Register!$M$5:$M$54,F$18,Register!$N$5:$N$54,$B20) -> 0 | G20: =COUNTIFS(Register!$M$5:$M$54,G$18,Register!$N$5:$N$54,$B20) -> 0
B21: 3 | C21: =COUNTIFS(Register!$M$5:$M$54,C$18,Register!$N$5:$N$54,$B21) -> 5 | D21: =COUNTIFS(Register!$M$5:$M$54,D$18,Register!$N$5:$N$54,$B21) -> 1 | E21: =COUNTIFS(Register!$M$5:$M$54,E$18,Register!$N$5:$N$54,$B21) -> 0 | F21: =COUNTIFS(Register!$M$5:$M$54,F$18,Register!$N$5:$N$54,$B21) -> 0 | G21: =COUNTIFS(Register!$M$5:$M$54,G$18,Register!$N$5:$N$54,$B21) -> 0
B22: 2 | C22: =COUNTIFS(Register!$M$5:$M$54,C$18,Register!$N$5:$N$54,$B22) -> 0 | D22: =COUNTIFS(Register!$M$5:$M$54,D$18,Register!$N$5:$N$54,$B22) -> 0 | E22: =COUNTIFS(Register!$M$5:$M$54,E$18,Register!$N$5:$N$54,$B22) -> 0 | F22: =COUNTIFS(Register!$M$5:$M$54,F$18,Register!$N$5:$N$54,$B22) -> 0 | G22: =COUNTIFS(Register!$M$5:$M$54,G$18,Register!$N$5:$N$54,$B22) -> 0
B23: 1 | C23: =COUNTIFS(Register!$M$5:$M$54,C$18,Register!$N$5:$N$54,$B23) -> 0 | D23: =COUNTIFS(Register!$M$5:$M$54,D$18,Register!$N$5:$N$54,$B23) -> 0 | E23: =COUNTIFS(Register!$M$5:$M$54,E$18,Register!$N$5:$N$54,$B23) -> 0 | F23: =COUNTIFS(Register!$M$5:$M$54,F$18,Register!$N$5:$N$54,$B23) -> 0 | G23: =COUNTIFS(Register!$M$5:$M$54,G$18,Register!$N$5:$N$54,$B23) -> 0
B24: Total | C24: =SUM(C19:G23) -> 15

Sheet Summary
A1: Risk Summary
A2: All figures are formulas over the Register sheet.
A4: Risks by rating | E4: Key figures
A5: Rating | B5: Inherent | C5: Residual | E5: Average inherent score | G5: =AVERAGE(Register!$H$5:$H$54) -> 13.066667
A6: Critical | B6: =COUNTIF(Register!$I$5:$I$54,A6) -> 7 | C6: =COUNTIF(Register!$P$5:$P$54,A6) -> 0 | E6: Average residual score | G6: =AVERAGE(Register!$O$5:$O$54) -> 5.0666667
A7: High | B7: =COUNTIF(Register!$I$5:$I$54,A7) -> 4 | C7: =COUNTIF(Register!$P$5:$P$54,A7) -> 2 | E7: Average risk reduction | G7: =AVERAGE(Register!$Q$5:$Q$54) -> 0.60333333
A8: Medium | B8: =COUNTIF(Register!$I$5:$I$54,A8) -> 4 | C8: =COUNTIF(Register!$P$5:$P$54,A8) -> 5 | E8: Open or in-progress risks | G8: =COUNTIF(Register!$R$5:$R$54,"Open")+COUNTIF(Register!$R$5:$R$54,"In Progress") -> 14
A9: Low | B9: =COUNTIF(Register!$I$5:$I$54,A9) -> 0 | C9: =COUNTIF(Register!$P$5:$P$54,A9) -> 8 | E9: Overdue mitigations | G9: =COUNTIF(Register!$U$5:$U$54,"OVERDUE") -> 1
A10: Total | B10: =SUM(B6:B9) -> 15 | C10: =SUM(C6:C9) -> 15
A12: Risks by status | E12: Risks by source
A13: Status | B13: Count | E13: Source | G13: Count
A14: Open | B14: =COUNTIF(Register!$R$5:$R$54,A14) -> 11 | E14: ITGC Testing | G14: =COUNTIF(Register!$D$5:$D$54,E14) -> 4
A15: In Progress | B15: =COUNTIF(Register!$R$5:$R$54,A15) -> 3 | E15: Vulnerability Assessment | G15: =COUNTIF(Register!$D$5:$D$54,E15) -> 4
A16: Closed | B16: =COUNTIF(Register!$R$5:$R$54,A16) -> 1 | E16: Enterprise Register | G16: =COUNTIF(Register!$D$5:$D$54,E16) -> 7
A19: Risks by category
A20: Category | B20: Count | C20: Total inherent score
A21: Access Control | B21: =COUNTIF(Register!$C$5:$C$54,A21) -> 4 | C21: =SUMIF(Register!$C$5:$C$54,A21,Register!$H$5:$H$54) -> 52
A22: Change Management | B22: =COUNTIF(Register!$C$5:$C$54,A22) -> 1 | C22: =SUMIF(Register!$C$5:$C$54,A22,Register!$H$5:$H$54) -> 16
A23: Segregation of Duties | B23: =COUNTIF(Register!$C$5:$C$54,A23) -> 1 | C23: =SUMIF(Register!$C$5:$C$54,A23,Register!$H$5:$H$54) -> 12
A24: Network Security | B24: =COUNTIF(Register!$C$5:$C$54,A24) -> 2 | C24: =SUMIF(Register!$C$5:$C$54,A24,Register!$H$5:$H$54) -> 35
A25: Data Protection | B25: =COUNTIF(Register!$C$5:$C$54,A25) -> 3 | C25: =SUMIF(Register!$C$5:$C$54,A25,Register!$H$5:$H$54) -> 27
A26: Vulnerability Management | B26: =COUNTIF(Register!$C$5:$C$54,A26) -> 1 | C26: =SUMIF(Register!$C$5:$C$54,A26,Register!$H$5:$H$54) -> 20
A27: Incident Response | B27: =COUNTIF(Register!$C$5:$C$54,A27) -> 1 | C27: =SUMIF(Register!$C$5:$C$54,A27,Register!$H$5:$H$54) -> 15
A28: Business Continuity | B28: =COUNTIF(Register!$C$5:$C$54,A28) -> 1 | C28: =SUMIF(Register!$C$5:$C$54,A28,Register!$H$5:$H$54) -> 10
A29: Third-Party Risk | B29: =COUNTIF(Register!$C$5:$C$54,A29) -> 1 | C29: =SUMIF(Register!$C$5:$C$54,A29,Register!$H$5:$H$54) -> 9
A30: Total | B30: =SUM(B21:B29) -> 15 | C30: =SUM(C21:C29) -> 196
A32: Top 5 risks by inherent score
A33: Rank | B33: Risk ID | C33: Title | D33: Inherent | E33: Rating | F33: Residual | G33: Owner | H33: Status
A34: 1 | B34: =INDEX(Register!$A$5:$A$54,MATCH(LARGE(Register!$V$5:$V$54,1),Register!$V$5:$V$54,0)) -> R-05 | C34: =INDEX(Register!$B$5:$B$54,MATCH(LARGE(Register!$V$5:$V$54,1),Register!$V$5:$V$54,0)) -> Customer database reachable from the public internet | D34: =INDEX(Register!$H$5:$H$54,MATCH(LARGE(Register!$V$5:$V$54,1),Register!$V$5:$V$54,0)) -> 20 | E34: =INDEX(Register!$I$5:$I$54,MATCH(LARGE(Register!$V$5:$V$54,1),Register!$V$5:$V$54,0)) -> Critical | F34: =INDEX(Register!$O$5:$O$54,MATCH(LARGE(Register!$V$5:$V$54,1),Register!$V$5:$V$54,0)) -> 5 | G34: =INDEX(Register!$J$5:$J$54,MATCH(LARGE(Register!$V$5:$V$54,1),Register!$V$5:$V$54,0)) -> IT Infrastructure | H34: =INDEX(Register!$R$5:$R$54,MATCH(LARGE(Register!$V$5:$V$54,1),Register!$V$5:$V$54,0)) -> Open
A35: 2 | B35: =INDEX(Register!$A$5:$A$54,MATCH(LARGE(Register!$V$5:$V$54,2),Register!$V$5:$V$54,0)) -> R-09 | C35: =INDEX(Register!$B$5:$B$54,MATCH(LARGE(Register!$V$5:$V$54,2),Register!$V$5:$V$54,0)) -> Unpatched ERP server vulnerability | D35: =INDEX(Register!$H$5:$H$54,MATCH(LARGE(Register!$V$5:$V$54,2),Register!$V$5:$V$54,0)) -> 20 | E35: =INDEX(Register!$I$5:$I$54,MATCH(LARGE(Register!$V$5:$V$54,2),Register!$V$5:$V$54,0)) -> Critical | F35: =INDEX(Register!$O$5:$O$54,MATCH(LARGE(Register!$V$5:$V$54,2),Register!$V$5:$V$54,0)) -> 10 | G35: =INDEX(Register!$J$5:$J$54,MATCH(LARGE(Register!$V$5:$V$54,2),Register!$V$5:$V$54,0)) -> IT Infrastructure | H35: =INDEX(Register!$R$5:$R$54,MATCH(LARGE(Register!$V$5:$V$54,2),Register!$V$5:$V$54,0)) -> In Progress
A36: 3 | B36: =INDEX(Register!$A$5:$A$54,MATCH(LARGE(Register!$V$5:$V$54,3),Register!$V$5:$V$54,0)) -> R-01 | C36: =INDEX(Register!$B$5:$B$54,MATCH(LARGE(Register!$V$5:$V$54,3),Register!$V$5:$V$54,0)) -> Terminated users retain active ERP access | D36: =INDEX(Register!$H$5:$H$54,MATCH(LARGE(Register!$V$5:$V$54,3),Register!$V$5:$V$54,0)) -> 16 | E36: =INDEX(Register!$I$5:$I$54,MATCH(LARGE(Register!$V$5:$V$54,3),Register!$V$5:$V$54,0)) -> Critical | F36: =INDEX(Register!$O$5:$O$54,MATCH(LARGE(Register!$V$5:$V$54,3),Register!$V$5:$V$54,0)) -> 4 | G36: =INDEX(Register!$J$5:$J$54,MATCH(LARGE(Register!$V$5:$V$54,3),Register!$V$5:$V$54,0)) -> IT Security | H36: =INDEX(Register!$R$5:$R$54,MATCH(LARGE(Register!$V$5:$V$54,3),Register!$V$5:$V$54,0)) -> In Progress
A37: 4 | B37: =INDEX(Register!$A$5:$A$54,MATCH(LARGE(Register!$V$5:$V$54,4),Register!$V$5:$V$54,0)) -> R-03 | C37: =INDEX(Register!$B$5:$B$54,MATCH(LARGE(Register!$V$5:$V$54,4),Register!$V$5:$V$54,0)) -> Production changes without independent approval | D37: =INDEX(Register!$H$5:$H$54,MATCH(LARGE(Register!$V$5:$V$54,4),Register!$V$5:$V$54,0)) -> 16 | E37: =INDEX(Register!$I$5:$I$54,MATCH(LARGE(Register!$V$5:$V$54,4),Register!$V$5:$V$54,0)) -> Critical | F37: =INDEX(Register!$O$5:$O$54,MATCH(LARGE(Register!$V$5:$V$54,4),Register!$V$5:$V$54,0)) -> 8 | G37: =INDEX(Register!$J$5:$J$54,MATCH(LARGE(Register!$V$5:$V$54,4),Register!$V$5:$V$54,0)) -> IT Infrastructure | H37: =INDEX(Register!$R$5:$R$54,MATCH(LARGE(Register!$V$5:$V$54,4),Register!$V$5:$V$54,0)) -> Open
A38: 5 | B38: =INDEX(Register!$A$5:$A$54,MATCH(LARGE(Register!$V$5:$V$54,5),Register!$V$5:$V$54,0)) -> R-06 | C38: =INDEX(Register!$B$5:$B$54,MATCH(LARGE(Register!$V$5:$V$54,5),Register!$V$5:$V$54,0)) -> Automated scanners find the exposed database | D38: =INDEX(Register!$H$5:$H$54,MATCH(LARGE(Register!$V$5:$V$54,5),Register!$V$5:$V$54,0)) -> 15 | E38: =INDEX(Register!$I$5:$I$54,MATCH(LARGE(Register!$V$5:$V$54,5),Register!$V$5:$V$54,0)) -> Critical | F38: =INDEX(Register!$O$5:$O$54,MATCH(LARGE(Register!$V$5:$V$54,5),Register!$V$5:$V$54,0)) -> 3 | G38: =INDEX(Register!$J$5:$J$54,MATCH(LARGE(Register!$V$5:$V$54,5),Register!$V$5:$V$54,0)) -> IT Infrastructure | H38: =INDEX(Register!$R$5:$R$54,MATCH(LARGE(Register!$V$5:$V$54,5),Register!$V$5:$V$54,0)) -> Open

Sheet Scale
A1: Scoring Scale and Settings
A4: Rating | B4: Min score | C4: Meaning
A5: Low | B5: 1 | C5: Accept or monitor
A6: Medium | B6: 5 | C6: Mitigate within the planning cycle
A7: High | B7: 10 | C7: Mitigate with an owner and a dated plan
A8: Critical | B8: 15 | C8: Escalate to management; mitigate first
A10: Settings
A11: Report as-of date | B11: 46325 | C11: Input. Fixed so results are reproducible; replace with =TODAY() for a live view.
A14: Likelihood | B14: Level | C14: Definition
A15: 1 | B15: Rare | C15: Not expected in the next 12 months
A16: 2 | B16: Unlikely | C16: Could occur, but no recent indicators
A17: 3 | B17: Possible | C17: Has occurred in similar organizations or shows some indicators
A18: 4 | B18: Likely | C18: Weakness is confirmed and exploitable with little effort
A19: 5 | B19: Almost certain | C19: Exposed now or already occurring
A21: Impact | B21: Level | C21: Definition
A22: 1 | B22: Minimal | C22: Negligible cost or disruption
A23: 2 | B23: Minor | C23: Limited disruption, absorbed in normal operations
A24: 3 | B24: Moderate | C24: Noticeable disruption or loss of one function or dataset
A25: 4 | B25: Major | C25: Financial reporting error, data breach or audit finding
A26: 5 | B26: Severe | C26: Material misstatement, large breach or extended outage
